cvxportfolio/__init__.py
cvxportfolio/cache.py
cvxportfolio/costs.py
cvxportfolio/errors.py
cvxportfolio/estimator.py
cvxportfolio/forecast.py
cvxportfolio/hyperparameters.py
cvxportfolio/policies.py
cvxportfolio/result.py
cvxportfolio/returns.py
cvxportfolio/risks.py
cvxportfolio/simulator.py
cvxportfolio/utils.py
cvxportfolio/constraints/__init__.py
cvxportfolio/constraints/base_constraints.py
cvxportfolio/constraints/constraints.py
cvxportfolio/data/__init__.py
cvxportfolio/data/market_data.py
cvxportfolio/data/symbol_data.py
cvxportfolio/tests/__init__.py
cvxportfolio/tests/__main__.py
cvxportfolio/tests/returns.csv
cvxportfolio/tests/sigmas.csv
cvxportfolio/tests/test_constraints.py
cvxportfolio/tests/test_costs.py
cvxportfolio/tests/test_data.py
cvxportfolio/tests/test_estimator.py
cvxportfolio/tests/test_forecast.py
cvxportfolio/tests/test_hyperparameters.py
cvxportfolio/tests/test_integration.py
cvxportfolio/tests/test_policies.py
cvxportfolio/tests/test_result.py
cvxportfolio/tests/test_returns.py
cvxportfolio/tests/test_risks.py
cvxportfolio/tests/test_simulator.py
cvxportfolio/tests/test_utils.py
cvxportfolio/tests/volumes.csv
cvxportfolio-1.5.1.dist-info/licenses/AUTHORS
cvxportfolio-1.5.1.dist-info/licenses/LICENSE
cvxportfolio-1.5.1.dist-info/METADATA
cvxportfolio-1.5.1.dist-info/WHEEL
cvxportfolio-1.5.1.dist-info/top_level.txt
cvxportfolio-1.5.1.dist-info/RECORD
