Metadata-Version: 2.4
Name: cvxportfolio
Version: 1.5.1
Summary: Portfolio optimization and back-testing.
Author: Enzo Busseti, Stephen Boyd, Steven Diamond, BlackRock Inc.
Maintainer-email: Enzo Busseti <enzo.busseti@gmail.com>
License: GPLv3
Project-URL: Homepage, https://www.cvxportfolio.com
Project-URL: Repository, https://github.com/cvxgrp/cvxportfolio
License-File: LICENSE
License-File: AUTHORS
Requires-Dist: pandas
Requires-Dist: numpy
Requires-Dist: matplotlib
Requires-Dist: cvxpy
Requires-Dist: curl_cffi; python_version >= "3.9"
Requires-Dist: requests; python_version < "3.9"
Requires-Dist: scs
Provides-Extra: docs
Requires-Dist: sphinx; extra == "docs"
Requires-Dist: pydata_sphinx_theme; extra == "docs"
Requires-Dist: sphinx-github-style; extra == "docs"
Requires-Dist: setuptools-scm; extra == "docs"
Provides-Extra: dev
Requires-Dist: build; extra == "dev"
Requires-Dist: twine; extra == "dev"
Requires-Dist: diff_cover; extra == "dev"
Requires-Dist: pylint; extra == "dev"
Requires-Dist: isort; extra == "dev"
Requires-Dist: setuptools-scm; extra == "dev"
Requires-Dist: autopep8; extra == "dev"
Requires-Dist: docformatter; extra == "dev"
Requires-Dist: beautifulsoup4; extra == "dev"
Requires-Dist: rstcheck; extra == "dev"
Provides-Extra: examples
Requires-Dist: beautifulsoup4; extra == "examples"
Requires-Dist: lxml; extra == "examples"
Requires-Dist: clarabel; extra == "examples"
Requires-Dist: ecos; extra == "examples"
Provides-Extra: test
Requires-Dist: ecos; extra == "test"
Requires-Dist: coverage[toml]; extra == "test"
Dynamic: license-file
